{
  "timestamp": "2026-07-20T00:08:18.262Z",
  "summary": {
    "total": 13,
    "online": 12,
    "offline": 1,
    "avgLatency": 635
  },
  "servers": [
    {
      "name": "SG VIP",
      "host": "ssl-sgvip.rajaserver.web.id",
      "ping": 290,
      "port80": {
        "status": "open",
        "latency": 294
      },
      "port443": {
        "status": "open",
        "latency": 290
      },
      "overall": "online"
    },
    {
      "name": "SG VVIP",
      "host": "ssl-sgvvip.rajaserver.web.id",
      "ping": 385,
      "port80": {
        "status": "open",
        "latency": 379
      },
      "port443": {
        "status": "open",
        "latency": 385
      },
      "overall": "online"
    },
    {
      "name": "SG VVIP 2",
      "host": "ssl-sgvvip2.rajaserver.web.id",
      "ping": 402,
      "port80": {
        "status": "open",
        "latency": 400
      },
      "port443": {
        "status": "open",
        "latency": 402
      },
      "overall": "online"
    },
    {
      "name": "SG VVIP 3",
      "host": "ssl-sgvvip3.rajaserver.web.id",
      "ping": 421,
      "port80": {
        "status": "open",
        "latency": 422
      },
      "port443": {
        "status": "open",
        "latency": 421
      },
      "overall": "online"
    },
    {
      "name": "ID Biznet VIP",
      "host": "ssl-idbiznetvip.rajaserver.web.id",
      "ping": 501,
      "port80": {
        "status": "open",
        "latency": 501
      },
      "port443": {
        "status": "open",
        "latency": 501
      },
      "overall": "online"
    },
    {
      "name": "ID Biznet VIP 2",
      "host": "ssl-idbiznetvip2.rajaserver.web.id",
      "ping": 603,
      "port80": {
        "status": "open",
        "latency": 603
      },
      "port443": {
        "status": "open",
        "latency": 603
      },
      "overall": "online"
    },
    {
      "name": "ID Biznet VIP 3",
      "host": "ssl-idbiznetvip3.rajaserver.web.id",
      "ping": 630,
      "port80": {
        "status": "open",
        "latency": 640
      },
      "port443": {
        "status": "open",
        "latency": 630
      },
      "overall": "online"
    },
    {
      "name": "EDU-1 DIRECT",
      "host": "eduserv1.aiosc.my.id",
      "ping": 758,
      "port80": {
        "status": "open",
        "latency": 758
      },
      "port443": {
        "status": "open",
        "latency": 758
      },
      "overall": "online"
    },
    {
      "name": "EDU-2 DIRECT",
      "host": "eduserv2.aiosc.my.id",
      "ping": 879,
      "port80": {
        "status": "open",
        "latency": 870
      },
      "port443": {
        "status": "open",
        "latency": 879
      },
      "overall": "online"
    },
    {
      "name": "EDU-3 DIRECT",
      "host": "eduserv3.aiosc.my.id",
      "ping": 918,
      "port80": {
        "status": "open",
        "latency": 915
      },
      "port443": {
        "status": "open",
        "latency": 918
      },
      "overall": "online"
    },
    {
      "name": "CLOUDFRONT REGULER",
      "host": "d1lnzdlpso56a0.cloudfront.net",
      "ping": 778,
      "port80": {
        "status": "open",
        "latency": 779
      },
      "port443": {
        "status": "open",
        "latency": 778
      },
      "overall": "online"
    },
    {
      "name": "VIP CLOUDFRONT PREMIUM",
      "host": "d1jrahl0hl8ghp.cloudfront.net",
      "ping": null,
      "port80": {
        "status": "closed",
        "latency": 825,
        "detail": "ENOTFOUND"
      },
      "port443": {
        "status": "closed",
        "latency": 825,
        "detail": "ENOTFOUND"
      },
      "overall": "offline"
    },
    {
      "name": "BOT ALIBABA",
      "host": "alibaba.rajaserver.web.id",
      "ping": 1059,
      "port80": {
        "status": "open",
        "latency": 1067
      },
      "port443": {
        "status": "open",
        "latency": 1059
      },
      "overall": "online"
    }
  ]
}